pycaltransfer/__init__.py
pycaltransfer/caltransfer.py
pycaltransfer/utils.py
pycaltransfer-0.1.8.dist-info/LICENSE
pycaltransfer-0.1.8.dist-info/METADATA
pycaltransfer-0.1.8.dist-info/WHEEL
pycaltransfer-0.1.8.dist-info/top_level.txt
pycaltransfer-0.1.8.dist-info/RECORD
