Metadata-Version: 2.1
Name: pycaltransfer
Version: 0.1.8
Summary: Calibration transfer for chemometrics and spectral data applications
Home-page: https://gitlab.com/chemsoftware/python/pycaltransfer
Author: Valeria Fonseca Diaz
Author-email: valeria.fonseca.diaz@gmail.com
Classifier: Programming Language :: Python :: 3
Classifier: License :: OSI Approved :: MIT License
Classifier: Operating System :: OS Independent
Requires-Python: >=3.7
License-File: LICENSE
Requires-Dist: numpy (>=1.20)
Requires-Dist: matplotlib (>=3.3)
Requires-Dist: scikit-learn (>=0.24)
Requires-Dist: scipy (>=1.6)
